geotiff/__init__.py
geotiff/geotiff.py
geotiff/utils/__init__.py
geotiff/utils/crs_code_guess.py
tests/__init__.py
tests/test_geotiff.py
geotiff-0.2.10.dist-info/LICENSE
geotiff-0.2.10.dist-info/METADATA
geotiff-0.2.10.dist-info/WHEEL
geotiff-0.2.10.dist-info/top_level.txt
geotiff-0.2.10.dist-info/RECORD
